pyrcwa/RCWA.py
pyrcwa/__init__.py
pyrcwa/core.py
pyrcwa/main.py
pyrcwa/material.py
pyrcwa/matrix.py
pyrcwa/model.py
pyrcwa/settings.py
pyrcwa/solver.py
pyrcwa/source.py
pyrcwa/utils.py
PyRCWA-0.0.0.0.1.dist-info/METADATA
PyRCWA-0.0.0.0.1.dist-info/WHEEL
PyRCWA-0.0.0.0.1.dist-info/top_level.txt
PyRCWA-0.0.0.0.1.dist-info/RECORD
