Metadata-Version: 2.1
Name: PyRCWA
Version: 0.0.0.0.1
Summary: An easy-use tools to simulate optical transmission
Home-page: https://github.com/vitamingcheng/PyRCWA
Author: Cheng Ming
Author-email: vitamingcheng@163.com
License: MIT
Keywords: PyRCWA
Platform: UNKNOWN
Classifier: Programming Language :: Python :: 3.8
Requires-Dist: numpy (>=1.21.6)
Requires-Dist: matplotlib (>=3.5.3)
Requires-Dist: scipy (>=1.7.3)
